gando/__init__.py
gando/admin.py
gando/apps.py
gando/models.py
gando/architectures/__init__.py
gando/architectures/admin/__init__.py
gando/architectures/admin/models/__init__.py
gando/architectures/apis/__base.py
gando/architectures/apis/__init__.py
gando/architectures/apis/helpertools/__init__.py
gando/architectures/apis/helpertools/structures.py
gando/architectures/interfaces/__base.py
gando/architectures/interfaces/__init__.py
gando/architectures/models/__init__.py
gando/architectures/models/fields/__init__.py
gando/architectures/models/serializers/__init__.py
gando/architectures/serializers/__init__.py
gando/architectures/serializers/base.py
gando/architectures/services/__base.py
gando/architectures/services/__creator.py
gando/architectures/services/__database_manager.py
gando/architectures/services/__getter.py
gando/architectures/services/__getter_creator.py
gando/architectures/services/__init__.py
gando/architectures/services/__updater.py
gando/auth/__init__.py
gando/auth/middlewares/__init__.py
gando/config/__init__.py
gando/http/__init__.py
gando/http/api_exceptions/__init__.py
gando/http/api_exceptions/base.py
gando/http/api_exceptions/developers/__init__.py
gando/http/api_exceptions/developers/base.py
gando/http/api_exceptions/developers/definitions.py
gando/http/api_exceptions/developers/errors.py
gando/http/api_exceptions/developers/exceptions.py
gando/http/api_exceptions/developers/warnings.py
gando/http/api_exceptions/endusers/__init__.py
gando/http/api_exceptions/endusers/base.py
gando/http/api_exceptions/endusers/definitions.py
gando/http/api_exceptions/endusers/errors.py
gando/http/api_exceptions/endusers/fail.py
gando/http/api_exceptions/endusers/warnings.py
gando/http/requests/__init__.py
gando/http/requests/func/__asyncio.py
gando/http/requests/func/__init__.py
gando/http/requests/methods/__init__.py
gando/http/requests/schemas/__init__.py
gando/http/requests/schemas/__request.py
gando/http/responses/__init__.py
gando-1.0.4.dist-info/licenses/LICENSE
gando-1.0.4.dist-info/METADATA
gando-1.0.4.dist-info/WHEEL
gando-1.0.4.dist-info/top_level.txt
gando-1.0.4.dist-info/RECORD
